Metadata-Version: 1.0
Name: Gaussian-Bionomial-Distributions
Version: 0.1
Summary: Gaussian_Bionomial_Distributions
Home-page: UNKNOWN
Author: UNKNOWN
Author-email: UNKNOWN
License: UNKNOWN
Platform: UNKNOWN
